tmp_hatchlor/__init__.py
tmp_hatchlor/_version.py
tmp_hatchlor/skeleton.py
tmp_hatchlor-0.1.0.dist-info/METADATA
tmp_hatchlor-0.1.0.dist-info/WHEEL
tmp_hatchlor-0.1.0.dist-info/entry_points.txt
tmp_hatchlor-0.1.0.dist-info/licenses/AUTHORS.md
tmp_hatchlor-0.1.0.dist-info/licenses/LICENSE.txt
tmp_hatchlor-0.1.0.dist-info/RECORD
