Metadata-Version: 2.3
Name: tmp-hatchlor
Version: 0.1.0
Summary: Python project featuring the modern and extensible Python project manager hatch.
Project-URL: Documentation, https://github.com/turboBasic/tmp-hatchlor
Project-URL: Source, https://github.com/turboBasic/tmp-hatchlor
Author-email: Andrii Melnyk <andrii7melnyk@proton.me>
License: MIT
License-File: AUTHORS.md
License-File: LICENSE.txt
Keywords: keyword_1,keyword_2
Classifier: Development Status :: 2 - Pre-Alpha
Classifier: Programming Language :: Python
Classifier: Programming Language :: Python :: 3.11
Classifier: Programming Language :: Python :: 3.12
Classifier: Programming Language :: Python :: Implementation :: CPython
Requires-Python: >=3.11
Requires-Dist: typer
